{
    "EquivalentNumberOfAtts": {
        "ourName": "EquivalentNumberOfFeatures",
        "multiplier": 1
    },
    "MeanCardinalityOfNominalAttributes": {
        "ourName": "MeanCardinalityOfNominalFeatures",
        "multiplier": 1
    },
    "StdevCardinalityOfNominalAttributes": {
        "ourName": "StdevCardinalityOfNominalFeatures",
        "multiplier": 1
    },
    "MaxCardinalityOfNominalAttributes": {
        "ourName": "MaxCardinalityOfNominalFeatures",
        "multiplier": 1
    },
    "MinCardinalityOfNominalFeatures": {
        "ourName": "MinCardinalityOfNominalAttributes",
        "multiplier": 1
    },
    "MeanCardinalityOfNumericAttributes": {
        "ourName": "MeanCardinalityOfNumericFeatures",
        "multiplier": 1
    },
    "StdevCardinalityOfNumericAttributes": {
        "ourName": "StdevCardinalityOfNumericFeatures",
        "multiplier": 1
    },
    "MaxCardinalityOfNumericAttributes": {
        "ourName": "MaxCardinalityOfNumericFeatures",
        "multiplier": 1
    },
    "MinCardinalityOfNumericAttributes": {
        "ourName": "MinCardinalityOfNumericFeatures",
        "multiplier": 1
    },
    "MinorityClassPercentage": {
        "ourName": "MinClassProbability",
        "multiplier": 100
    },
    "MajorityClassPercentage": {
        "ourName": "MaxClassProbability",
        "multiplier": 100
    },
    "MaxMeansOfNumericAtts": {
        "ourName": "MaxMeansOfNumericFeatures",
        "multiplier": 1
    },
    "MaxStdevOfNumericAtts": {
        "ourName": "MaxStdevOfNumericFeatures",
        "multiplier": 1
    },
    "MaxSkewnessOfNumericAtts": {
        "ourName": "MaxSkewnessOfNumericFeatures",
        "multiplier": 1
    },
    "MaxKurtosisOfNumericAtts": {
        "ourName": "MaxKurtosisOfNumericFeatures",
        "multiplier": 1
    },
    "MinMeansOfNumericAtts": {
        "ourName": "MinMeansOfNumericFeatures",
        "multiplier": 1
    },
    "MinStdevOfNumericAtts": {
        "ourName": "MinStdevOfNumericFeatures",
        "multiplier": 1
    },
    "MinSkewnessOfNumericAtts": {
        "ourName": "MinSkewnessOfNumericFeatures",
        "multiplier": 1
    },
    "MinKurtosisOfNumericAtts": {
        "ourName": "MinKurtosisOfNumericFeatures",
        "multiplier": 1
    },
    "MeanMeansOfNumericAtts": {
        "ourName": "MeanMeansOfNumericFeatures",
        "multiplier": 1
    },
    "MeanStdevOfNumericAtts": {
        "ourName": "MeanStdevOfNumericFeatures",
        "multiplier": 1
    },
    "MeanSkewnessOfNumericAtts": {
        "ourName": "MeanSkewnessOfNumericFeatures",
        "multiplier": 1
    },
    "MeanKurtosisOfNumericAtts": {
        "ourName": "MeanKurtosisOfNumericFeatures",
        "multiplier": 1
    },
    "StdevMeansOfNumericAtts": {
        "ourName": "StdevMeansOfNumericFeatures",
        "multiplier": 1
    },
    "StdevStdevOfNumericAtts": {
        "ourName": "StdevStdevOfNumericFeatures",
        "multiplier": 1
    },
    "StdevSkewnessOfNumericAtts": {
        "ourName": "StdevSkewnessOfNumericFeatures",
        "multiplier": 1
    },
    "StdevKurtosisOfNumericAtts": {
        "ourName": "StdevKurtosisOfNumericFeatures",
        "multiplier": 1
    },
    "Quartile1MeansOfNumericAtts": {
        "ourName": "Quartile1MeansOfNumericFeatures",
        "multiplier": 1
    },
    "Quartile1StdevOfNumericAtts": {
        "ourName": "Quartile1StdevOfNumericFeatures",
        "multiplier": 1
    },
    "Quartile1SkewnessOfNumericAtts": {
        "ourName": "Quartile1SkewnessOfNumericFeatures",
        "multiplier": 1
    },
    "Quartile1KurtosisOfNumericAtts": {
        "ourName": "Quartile1KurtosisOfNumericFeatures",
        "multiplier": 1
    },
    "Quartile2MeansOfNumericAtts": {
        "ourName": "Quartile2MeansOfNumericFeatures",
        "multiplier": 1
    },
    "Quartile2StdevOfNumericAtts": {
        "ourName": "Quartile2StdevOfNumericFeatures",
        "multiplier": 1
    },
    "Quartile2SkewnessOfNumericAtts": {
        "ourName": "Quartile2SkewnessOfNumericFeatures",
        "multiplier": 1
    },
    "Quartile2KurtosisOfNumericAtts": {
        "ourName": "Quartile2KurtosisOfNumericFeatures",
        "multiplier": 1
    },
    "Quartile3MeansOfNumericAtts": {
        "ourName": "Quartile3MeansOfNumericFeatures",
        "multiplier": 1
    },
    "Quartile3StdevOfNumericAtts": {
        "ourName": "Quartile3StdevOfNumericFeatures",
        "multiplier": 1
    },
    "Quartile3SkewnessOfNumericAtts": {
        "ourName": "Quartile3SkewnessOfNumericFeatures",
        "multiplier": 1
    },
    "Quartile3KurtosisOfNumericAtts": {
        "ourName": "Quartile3KurtosisOfNumericFeatures",
        "multiplier": 1
    },
    "PercentageOfInstancesWithMissingValues": {
        "ourName": "RatioOfInstancesWithMissingValues",
        "multiplier": 100
    },
    "PercentageOfMissingValues": {
        "ourName": "RatioOfMissingValues",
        "multiplier": 100
    },
    "PercentageOfNumericFeatures": {
        "ourName": "RatioOfNumericFeatures",
        "multiplier": 100
    },
    "PercentageOfSymbolicFeatures": {
        "ourName": "RatioOfNominalFeatures",
        "multiplier": 100
    },
    "Dimensionality": {
        "ourName": "Dimensionality",
        "multiplier": 1
    },
    "MajorityClassSize": {
        "ourName": "MajorityClassSize",
        "multiplier": 1
    },
    "MeanAttributeEntropy": {
        "ourName": "MeanAttributeEntropy",
        "multiplier": 1
    },
    "MinAttributeEntropy": {
        "ourName": "MinAttributeEntropy",
        "multiplier": 1
    },
    "MinMutualInformation": {
        "ourName": "MinMutualInformation",
        "multiplier": 1
    },
    "MinorityClassSize": {
        "ourName": "MinorityClassSize",
        "multiplier": 1
    },
    "NumberOfClasses": {
        "ourName": "NumberOfClasses",
        "multiplier": 1
    },
    "NumberOfInstances": {
        "ourName": "NumberOfInstances",
        "multiplier": 1
    },
    "NumberOfMissingValues": {
        "ourName": "NumberOfMissingValues",
        "multiplier": 1
    },
    "Quartile1MutualInformation": {
        "ourName": "Quartile1MutualInformation",
        "multiplier": 1
    },
    "ClassEntropy": {
        "ourName": "ClassEntropy",
        "multiplier": 1
    },
    "DecisionStumpErrRate": {
        "ourName": "DecisionStumpErrRate",
        "multiplier": 1
    },
    "DecisionStumpKappa": {
        "ourName": "DecisionStumpKappa",
        "multiplier": 1
    },
    "MaxAttributeEntropy": {
        "ourName": "MaxAttributeEntropy",
        "multiplier": 1
    },
    "MaxMutualInformation": {
        "ourName": "MaxMutualInformation",
        "multiplier": 1
    },
    "MeanMutualInformation": {
        "ourName": "MeanMutualInformation",
        "multiplier": 1
    },
    "NaiveBayesErrRate": {
        "ourName": "NaiveBayesErrRate",
        "multiplier": 1
    },
    "NaiveBayesKappa": {
        "ourName": "NaiveBayesKappa",
        "multiplier": 1
    },
    "NumberOfFeatures": {
        "ourName": "NumberOfFeatures",
        "multiplier": 1
    },
    "NumberOfInstancesWithMissingValues": {
        "ourName": "NumberOfInstancesWithMissingValues",
        "multiplier": 1
    },
    "NumberOfNumericFeatures": {
        "ourName": "NumberOfNumericFeatures",
        "multiplier": 1
    },
    "NumberOfSymbolicFeatures": {
        "ourName": "NumberofNominalFeatures",
        "multiplier": 1
    },
    "Quartile1AttributeEntropy": {
        "ourName": "Quartile1AttributeEntropy",
        "multiplier": 1
    },
    "Quartile2AttributeEntropy": {
        "ourName": "Quartile2AttributeEntropy",
        "multiplier": 1
    },
    "Quartile2MutualInformation": {
        "ourName": "Quartile2MutualInformation",
        "multiplier": 1
    },
    "Quartile3AttributeEntropy": {
        "ourName": "Quartile3AttributeEntropy",
        "multiplier": 1
    },
    "Quartile3MutualInformation": {
        "ourName": "Quartile3MutualInformation",
        "multiplier": 1
    },
    "kNN1NErrRate": {
        "ourName": "kNN1NErrRate",
        "multiplier": 1
    },
    "kNN1NKappa": {
        "ourName": "kNN1NKappa",
        "multiplier": 1
    }
}